nonblocking_itertools/__init__.py
nonblocking_itertools-0.1.2.dist-info/WHEEL
nonblocking_itertools-0.1.2.dist-info/METADATA
nonblocking_itertools-0.1.2.dist-info/RECORD
