Metadata-Version: 2.1
Name: nonblocking-itertools
Version: 0.1.2
Summary: 
Author: Ben Skubi
Author-email: skubi@ohsu.edu
Requires-Python: >=3.10,<4.0
Classifier: Programming Language :: Python :: 3
Classifier: Programming Language :: Python :: 3.10
Requires-Dist: salish (>=0.1.0,<0.2.0)
